django_user_payments-0.3.3.dist-info/DESCRIPTION.rst
django_user_payments-0.3.3.dist-info/METADATA
django_user_payments-0.3.3.dist-info/RECORD
django_user_payments-0.3.3.dist-info/WHEEL
django_user_payments-0.3.3.dist-info/metadata.json
django_user_payments-0.3.3.dist-info/top_level.txt
user_payments/__init__.py
user_payments/admin.py
user_payments/apps.py
user_payments/exceptions.py
user_payments/models.py
user_payments/processing.py
user_payments/locale/de/LC_MESSAGES/django.mo
user_payments/locale/de/LC_MESSAGES/django.po
user_payments/migrations/0001_initial.py
user_payments/migrations/__init__.py
user_payments/stripe_customers/__init__.py
user_payments/stripe_customers/admin.py
user_payments/stripe_customers/apps.py
user_payments/stripe_customers/models.py
user_payments/stripe_customers/moochers.py
user_payments/stripe_customers/migrations/0001_initial.py
user_payments/stripe_customers/migrations/__init__.py
user_payments/stripe_customers/static/stripe_customers/cards.js
user_payments/stripe_customers/templates/stripe_customers/payment_form.html
user_payments/user_subscriptions/__init__.py
user_payments/user_subscriptions/admin.py
user_payments/user_subscriptions/apps.py
user_payments/user_subscriptions/models.py
user_payments/user_subscriptions/utils.py
user_payments/user_subscriptions/migrations/0001_initial.py
user_payments/user_subscriptions/migrations/__init__.py
