Metadata-Version: 2.0
Name: django-user-payments
Version: 0.3.3
Summary: User payments and subscriptions for Django
Home-page: https://github.com/matthiask/django-user-payments/
Author: Matthias Kestenholz
Author-email: mk@feinheit.ch
License: BSD License
Platform: OS Independent
Classifier: Environment :: Web Environment
Classifier: Framework :: Django
Classifier: Intended Audience :: Developers
Classifier: License :: OSI Approved :: BSD License
Classifier: Operating System :: OS Independent
Classifier: Programming Language :: Python
Classifier: Programming Language :: Python :: 3
Classifier: Programming Language :: Python :: 3.5
Classifier: Programming Language :: Python :: 3.6
Classifier: Programming Language :: Python :: 3.7
Classifier: Topic :: Internet :: WWW/HTTP :: Dynamic Content
Classifier: Topic :: Software Development
Classifier: Topic :: Software Development :: Libraries :: Application Frameworks
Provides-Extra: stripe
Requires-Dist: django-mooch
Provides-Extra: stripe
Requires-Dist: stripe (>=2); extra == 'stripe'
